{
  "ComponentAllowCustomization": true,
  "ComponentChangedSinceFileImport": false,
  "ComponentDefinitionInfo": {
    "AllowAccessToGlobals": false,
    "Children": [
      {
        "AllowAccessToGlobals": true,
        "Children": [],
        "ControlPropertyState": [
          "BorderColor",
          "BorderStyle",
          {
            "AFDDataSourceName": "",
            "AutoRuleBindingEnabled": false,
            "AutoRuleBindingString": "",
            "InvariantPropertyName": "Fill",
            "IsLockable": false,
            "NameMapSourceSchema": "?"
          },
          "X",
          "Y",
          {
            "AFDDataSourceName": "",
            "AutoRuleBindingEnabled": false,
            "AutoRuleBindingString": "1366",
            "InvariantPropertyName": "Width",
            "IsLockable": false,
            "NameMapSourceSchema": "?"
          },
          {
            "AFDDataSourceName": "",
            "AutoRuleBindingEnabled": false,
            "AutoRuleBindingString": "",
            "InvariantPropertyName": "Height",
            "IsLockable": false,
            "NameMapSourceSchema": "?"
          },
          "DisplayMode",
          "ChildTabPriority",
          "LayoutMode",
          "LayoutDirection",
          {
            "AFDDataSourceName": "",
            "AutoRuleBindingEnabled": false,
            "AutoRuleBindingString": "",
            "InvariantPropertyName": "LayoutAlignItems",
            "IsLockable": false,
            "NameMapSourceSchema": "?"
          },
          {
            "AFDDataSourceName": "",
            "AutoRuleBindingEnabled": false,
            "AutoRuleBindingString": "",
            "InvariantPropertyName": "LayoutJustifyContent",
            "IsLockable": false,
            "NameMapSourceSchema": "?"
          },
          {
            "AFDDataSourceName": "",
            "AutoRuleBindingEnabled": false,
            "AutoRuleBindingString": "",
            "InvariantPropertyName": "LayoutGap",
            "IsLockable": false,
            "NameMapSourceSchema": "?"
          },
          "LayoutOverflowX",
          "LayoutOverflowY",
          {
            "AFDDataSourceName": "",
            "AutoRuleBindingEnabled": false,
            "AutoRuleBindingString": "",
            "InvariantPropertyName": "LayoutWrap",
            "IsLockable": false,
            "NameMapSourceSchema": "?"
          },
          {
            "AFDDataSourceName": "",
            "AutoRuleBindingEnabled": false,
            "AutoRuleBindingString": "",
            "InvariantPropertyName": "DropShadow",
            "IsLockable": false,
            "NameMapSourceSchema": "?"
          },
          "ZIndex",
          {
            "AFDDataSourceName": "",
            "AutoRuleBindingEnabled": false,
            "AutoRuleBindingString": "",
            "InvariantPropertyName": "RadiusTopLeft",
            "IsLockable": false,
            "NameMapSourceSchema": "?"
          },
          {
            "AFDDataSourceName": "",
            "AutoRuleBindingEnabled": false,
            "AutoRuleBindingString": "",
            "InvariantPropertyName": "RadiusTopRight",
            "IsLockable": false,
            "NameMapSourceSchema": "?"
          },
          {
            "AFDDataSourceName": "",
            "AutoRuleBindingEnabled": false,
            "AutoRuleBindingString": "",
            "InvariantPropertyName": "RadiusBottomLeft",
            "IsLockable": false,
            "NameMapSourceSchema": "?"
          },
          {
            "AFDDataSourceName": "",
            "AutoRuleBindingEnabled": false,
            "AutoRuleBindingString": "",
            "InvariantPropertyName": "RadiusBottomRight",
            "IsLockable": false,
            "NameMapSourceSchema": "?"
          },
          {
            "AFDDataSourceName": "",
            "AutoRuleBindingEnabled": false,
            "AutoRuleBindingString": "",
            "InvariantPropertyName": "PaddingLeft",
            "IsLockable": false,
            "NameMapSourceSchema": "?"
          },
          {
            "AFDDataSourceName": "",
            "AutoRuleBindingEnabled": false,
            "AutoRuleBindingString": "",
            "InvariantPropertyName": "PaddingRight",
            "IsLockable": false,
            "NameMapSourceSchema": "?"
          }
        ],
        "ControlUniqueId": "13",
        "HasDynamicProperties": false,
        "Index": 0,
        "IsAutoGenerated": false,
        "IsDataControl": false,
        "IsFromScreenLayout": false,
        "IsGroupControl": false,
        "IsLocked": false,
        "LayoutName": "",
        "MetaDataIDKey": "",
        "Name": "Container5_1",
        "OptimizeForDevices": "Off",
        "Parent": "Header",
        "PersistMetaDataIDKey": false,
        "PublishOrderIndex": 2,
        "Rules": [
          {
            "Category": "Design",
            "InvariantScript": "RGBA(0, 0, 0, 1)",
            "Property": "BorderColor",
            "RuleProviderType": "Unknown"
          },
          {
            "Category": "Design",
            "InvariantScript": "BorderStyle.Solid",
            "Property": "BorderStyle",
            "RuleProviderType": "Unknown"
          },
          {
            "Category": "Design",
            "InvariantScript": "RGBA(0, 50, 100, 0.05)",
            "Property": "Fill",
            "RuleProviderType": "User"
          },
          {
            "Category": "Design",
            "InvariantScript": "0",
            "Property": "X",
            "RuleProviderType": "Unknown"
          },
          {
            "Category": "Design",
            "InvariantScript": "0",
            "Property": "Y",
            "RuleProviderType": "Unknown"
          },
          {
            "Category": "Design",
            "InvariantScript": "Parent.Width",
            "Property": "Width",
            "RuleProviderType": "Unknown"
          },
          {
            "Category": "Design",
            "InvariantScript": "60",
            "Property": "Height",
            "RuleProviderType": "Unknown"
          },
          {
            "Category": "Design",
            "InvariantScript": "DisplayMode.Edit",
            "Property": "DisplayMode",
            "RuleProviderType": "Unknown"
          },
          {
            "Category": "Design",
            "InvariantScript": "true",
            "Property": "ChildTabPriority",
            "RuleProviderType": "Unknown"
          },
          {
            "Category": "Design",
            "InvariantScript": "LayoutMode.Auto",
            "Property": "LayoutMode",
            "RuleProviderType": "Unknown"
          },
          {
            "Category": "Design",
            "InvariantScript": "LayoutDirection.Horizontal",
            "Property": "LayoutDirection",
            "RuleProviderType": "Unknown"
          },
          {
            "Category": "Design",
            "InvariantScript": "LayoutAlignItems.Center",
            "Property": "LayoutAlignItems",
            "RuleProviderType": "Unknown"
          },
          {
            "Category": "Design",
            "InvariantScript": "LayoutJustifyContent.End",
            "Property": "LayoutJustifyContent",
            "RuleProviderType": "Unknown"
          },
          {
            "Category": "Design",
            "InvariantScript": "20",
            "Property": "LayoutGap",
            "RuleProviderType": "Unknown"
          },
          {
            "Category": "Design",
            "InvariantScript": "LayoutOverflow.Hide",
            "Property": "LayoutOverflowX",
            "RuleProviderType": "Unknown"
          },
          {
            "Category": "Design",
            "InvariantScript": "LayoutOverflow.Hide",
            "Property": "LayoutOverflowY",
            "RuleProviderType": "Unknown"
          },
          {
            "Category": "Design",
            "InvariantScript": "false",
            "Property": "LayoutWrap",
            "RuleProviderType": "Unknown"
          },
          {
            "Category": "Design",
            "InvariantScript": "DropShadow.Light",
            "Property": "DropShadow",
            "RuleProviderType": "Unknown"
          },
          {
            "Category": "Design",
            "InvariantScript": "1",
            "Property": "ZIndex",
            "RuleProviderType": "Unknown"
          },
          {
            "Category": "Design",
            "InvariantScript": "0",
            "Property": "RadiusTopLeft",
            "RuleProviderType": "Unknown"
          },
          {
            "Category": "Design",
            "InvariantScript": "0",
            "Property": "RadiusTopRight",
            "RuleProviderType": "Unknown"
          },
          {
            "Category": "Design",
            "InvariantScript": "0",
            "Property": "RadiusBottomLeft",
            "RuleProviderType": "Unknown"
          },
          {
            "Category": "Design",
            "InvariantScript": "0",
            "Property": "RadiusBottomRight",
            "RuleProviderType": "Unknown"
          },
          {
            "Category": "Design",
            "InvariantScript": "30",
            "Property": "PaddingLeft",
            "RuleProviderType": "Unknown"
          },
          {
            "Category": "Design",
            "InvariantScript": "30",
            "Property": "PaddingRight",
            "RuleProviderType": "Unknown"
          }
        ],
        "StyleName": "defaultGroupContainerStyle",
        "Template": {
          "CustomGroupControlTemplateName": "",
          "FirstParty": true,
          "Id": "http://microsoft.com/appmagic/groupContainer",
          "IsComponentDefinition": false,
          "IsCustomGroupControlTemplate": false,
          "IsPremiumPcfControl": false,
          "LastModifiedTimestamp": "0",
          "Name": "groupContainer",
          "OverridableProperties": {},
          "Version": "1.3.0"
        },
        "Type": "ControlInfo",
        "VariantName": "horizontalAutoLayoutContainer"
      }
    ],
    "ControlPropertyState": [
      "Fill",
      {
        "AFDDataSourceName": "",
        "AutoRuleBindingEnabled": false,
        "AutoRuleBindingString": "",
        "InvariantPropertyName": "Height",
        "IsLockable": false,
        "NameMapSourceSchema": "?"
      },
      {
        "AFDDataSourceName": "",
        "AutoRuleBindingEnabled": false,
        "AutoRuleBindingString": "640",
        "InvariantPropertyName": "Width",
        "IsLockable": false,
        "NameMapSourceSchema": "?"
      },
      "X",
      "Y",
      "ZIndex"
    ],
    "LastModifiedTimestamp": "638452227824009986",
    "Name": "Header",
    "Rules": [
      {
        "Category": "Design",
        "InvariantScript": "2",
        "Property": "ZIndex",
        "RuleProviderType": "Unknown"
      },
      {
        "Category": "Design",
        "InvariantScript": "0",
        "Property": "Y",
        "RuleProviderType": "Unknown"
      },
      {
        "Category": "Design",
        "InvariantScript": "0",
        "Property": "X",
        "RuleProviderType": "Unknown"
      },
      {
        "Category": "Design",
        "InvariantScript": "Max(App.Width, App.MinScreenWidth) - 215",
        "Property": "Width",
        "RuleProviderType": "System"
      },
      {
        "Category": "Design",
        "InvariantScript": "60",
        "Property": "Height",
        "RuleProviderType": "Unknown"
      },
      {
        "Category": "Design",
        "InvariantScript": "RGBA(0, 0, 0, 0)",
        "Property": "Fill",
        "RuleProviderType": "System"
      }
    ]
  },
  "ComponentManifest": {
    "AllowAccessToGlobals": false,
    "AllowCustomization": true,
    "Description": "",
    "Name": "Header",
    "TemplateGuid": "5dacb9bfd5fc42bf8360703feb01900b"
  },
  "ComponentType": "CanvasComponent",
  "CustomGroupControlTemplateName": "",
  "CustomProperties": [],
  "FirstParty": true,
  "Id": "http://microsoft.com/appmagic/Component",
  "IsComponentLocked": false,
  "IsComponentTemplate": true,
  "IsCustomGroupControlTemplate": false,
  "IsPcfControl": false,
  "IsPremiumPcfControl": false,
  "IsWidgetTemplate": false,
  "LastModifiedTimestamp": "638452227824009986",
  "Name": "5dacb9bfd5fc42bf8360703feb01900b",
  "OverridableProperties": {},
  "TemplateOriginalName": "2f5527d107d940269b91ad64aaabe0ee",
  "Version": "1.0"
}